galaxygst/__init__.py
galaxygst/__main__.py
galaxygst/gst.py
galaxygst-1.0.1.dist-info/LICENSE
galaxygst-1.0.1.dist-info/METADATA
galaxygst-1.0.1.dist-info/WHEEL
galaxygst-1.0.1.dist-info/entry_points.txt
galaxygst-1.0.1.dist-info/top_level.txt
galaxygst-1.0.1.dist-info/RECORD
