Metadata-Version: 2.1
Name: galaxygst
Version: 1.0.1
Summary: Python tool to record GST object motion for Super Mario Galaxy 2
Home-page: https://github.com/SunakazeKun/galaxygst
Author: Aurum
License: gpl-3.0
Keywords: nintendo,super-mario-galaxy-2,gst,dolphin,modding
Classifier: Intended Audience :: Developers
Classifier: Topic :: Software Development :: Libraries
Classifier: License :: OSI Approved :: GNU General Public License v3 (GPLv3)
Classifier: Programming Language :: Python :: 3 :: Only
Requires-Python: >=3.10
License-File: LICENSE
Requires-Dist: dolphin-memory-engine
